{
    "sentence": "The British English spelling of this compound is hydrogen sulphide, but this spelling is not recommended by the International Union of Pure and Applied Chemistry (IUPAC) or the Royal Society of Chemistry.",
    "false_negative_tokens": [
        {
            "token": "British",
            "positive_examples": [
                {
                    "sentence": "...of family physicians the british medical association and the royal pharmaceutical...",
                    "entity": "British Medical Association"
                },
                {
                    "sentence": "...programmes winning the 2006 british academy television award for best drama series and five consecutive 2005...",
                    "entity": "British Academy Television Award for Best Drama Series"
                }
            ]
        }
    ]
}