{
    "sentence": "Their engagement with specific ideas relating to feminism, technoscience, political consciousness, and other social issues, formed the images and narrative of Haraway's book Modest _ Witness for which she received the Society for Social Studies of Science ' s (4S) Ludwik Fleck Prize in 1999.",
    "false_negative_tokens": [
        {
            "token": "consciousness",
            "entity_count": 1,
            "context_count": 0,
            "other_count": 0,
            "positive_examples": [
                {
                    "sentence": "Several scholars including Steven Pinker, Chomsky, Gerald Edelman, and Alexander Luria have indicated the importance of the emergence of human language as an important regulative mechanism of learning and memory in the context of the development of higher-order consciousness.",
                    "true_entities": [
                        {
                            "span": "Steven Pinker",
                            "entity": "Scientist"
                        },
                        {
                            "span": "Chomsky",
                            "entity": "Scientist"
                        },
                        {
                            "span": "Gerald Edelman",
                            "entity": "Scientist"
                        },
                        {
                            "span": "Alexander Luria",
                            "entity": "Scientist"
                        },
                        {
                            "span": "higher-order consciousness",
                            "entity": "Theory"
                        }
                    ]
                }
            ],
            "hard_negative_examples": [],
            "negative_examples": []
        }
    ]
}