{
    "sentence": "In 2013, WordFire acquired the reprint rights to the works of Allen Drury, including his 1959 Pulitzer Prize -winning political novel Advise and Consent.",
    "inside_boundary_tokens": [
        {
            "boundary": "inside",
            "token": "1959",
            "entity_str": "{'span': '1959', 'entity': 'Misc'}",
            "examples": [
                {
                    "sentence": "...richard condon author of the manchurian candidate 1959 prizzi s honor...",
                    "entity": "The Manchurian Candidate"
                },
                {
                    "sentence": "...the manchurian candidate 1959 prizzi s honor 1982 and numerous other...",
                    "entity": "Prizzi's Honor"
                }
            ]
        }
    ],
    "outside_boundary_tokens": []
}