{
    "id": 140,
    "sentence": "During the French Revolution, the unpopularity of the Directory led to riots and rebellions.",
    "classification": {
        "entity": [
            "French",
            "Revolution",
            "Directory"
        ],
        "context": [
            "During",
            "the",
            ",",
            "the",
            "of",
            "the",
            "led",
            "to"
        ],
        "other": [
            "unpopularity",
            "riots",
            "and",
            "rebellions",
            "."
        ]
    },
    "tokens": [
        "During",
        "the",
        "French",
        "Revolution",
        ",",
        "the",
        "unpopularity",
        "of",
        "the",
        "Directory",
        "led",
        "to",
        "riots",
        "and",
        "rebellions",
        "."
    ],
    "ner_tags": [
        0,
        0,
        15,
        16,
        0,
        0,
        0,
        0,
        0,
        27,
        0,
        0,
        0,
        0,
        0,
        0
    ],
    "true_entities": [
        {
            "span": "French Revolution",
            "entity": "Event"
        },
        {
            "span": "Directory",
            "entity": "Time"
        }
    ]
}