{
    "id": 196,
    "sentence": "Its design was modified to a military transport as the Tupolev Tu-75, but this was also not placed into production.",
    "classification": {
        "entity": [
            "Tupolev",
            "Tu-75"
        ],
        "context": [
            "as",
            "the",
            ",",
            "but"
        ],
        "other": [
            "Its",
            "design",
            "was",
            "modified",
            "to",
            "a",
            "military",
            "transport",
            "this",
            "was",
            "also",
            "not",
            "placed",
            "into",
            "production",
            "."
        ]
    },
    "tokens": [
        "Its",
        "design",
        "was",
        "modified",
        "to",
        "a",
        "military",
        "transport",
        "as",
        "the",
        "Tupolev",
        "Tu-75",
        ",",
        "but",
        "this",
        "was",
        "also",
        "not",
        "placed",
        "into",
        "production",
        "."
    ],
    "ner_tags": [
        0,
        0,
        0,
        0,
        0,
        0,
        0,
        0,
        0,
        0,
        29,
        30,
        0,
        0,
        0,
        0,
        0,
        0,
        0,
        0,
        0,
        0
    ],
    "true_entities": [
        {
            "span": "Tupolev Tu-75",
            "entity": "Vehicle"
        }
    ]
}