{
    "id": 58,
    "sentence": "According to one such tradition, she is the personification of the Earth itself; according to another, its actual mother, being \" Prithvi Tattwa \", the essence of the element earth.",
    "classification": {
        "entity": [
            "Earth",
            "Prithvi",
            "Tattwa"
        ],
        "context": [
            "of",
            "the",
            "itself",
            ";",
            "being",
            "\"",
            "\"",
            ","
        ],
        "other": [
            "According",
            "to",
            "one",
            "such",
            "tradition",
            ",",
            "she",
            "is",
            "the",
            "personification",
            "according",
            "to",
            "another",
            ",",
            "its",
            "actual",
            "mother",
            ",",
            "the",
            "essence",
            "of",
            "the",
            "element",
            "earth",
            "."
        ]
    },
    "tokens": [
        "According",
        "to",
        "one",
        "such",
        "tradition",
        ",",
        "she",
        "is",
        "the",
        "personification",
        "of",
        "the",
        "Earth",
        "itself",
        ";",
        "according",
        "to",
        "another",
        ",",
        "its",
        "actual",
        "mother",
        ",",
        "being",
        "\"",
        "Prithvi",
        "Tattwa",
        "\"",
        ",",
        "the",
        "essence",
        "of",
        "the",
        "element",
        "earth",
        "."
    ],
    "ner_tags": [
        0,
        0,
        0,
        0,
        0,
        0,
        0,
        0,
        0,
        0,
        0,
        0,
        11,
        0,
        0,
        0,
        0,
        0,
        0,
        0,
        0,
        0,
        0,
        0,
        0,
        23,
        24,
        0,
        0,
        0,
        0,
        0,
        0,
        0,
        0,
        0
    ],
    "true_entities": [
        {
            "span": "Earth",
            "entity": "Celestial Body"
        },
        {
            "span": "Prithvi Tattwa",
            "entity": "Mythological entity"
        }
    ]
}