{
    "id": 125,
    "sentence": "He then began working at the Institute of Tropical Medicine Antwerp while pursuing a graduate degree in clinical microbiology from the University of Antwerp.",
    "classification": {
        "entity": [
            "Institute",
            "of",
            "Tropical",
            "Medicine",
            "Antwerp",
            "clinical",
            "microbiology",
            "University",
            "of",
            "Antwerp"
        ],
        "context": [
            "at",
            "the",
            "while",
            "pursuing",
            "degree",
            "in",
            "from",
            "the",
            "."
        ],
        "other": [
            "He",
            "then",
            "began",
            "working",
            "a",
            "graduate"
        ]
    },
    "tokens": [
        "He",
        "then",
        "began",
        "working",
        "at",
        "the",
        "Institute",
        "of",
        "Tropical",
        "Medicine",
        "Antwerp",
        "while",
        "pursuing",
        "a",
        "graduate",
        "degree",
        "in",
        "clinical",
        "microbiology",
        "from",
        "the",
        "University",
        "of",
        "Antwerp",
        "."
    ],
    "ner_tags": [
        0,
        0,
        0,
        0,
        0,
        0,
        49,
        50,
        50,
        50,
        50,
        0,
        0,
        0,
        0,
        0,
        0,
        23,
        24,
        0,
        0,
        75,
        76,
        76,
        0
    ],
    "true_entities": [
        {
            "span": "Institute of Tropical Medicine Antwerp",
            "entity": "Organisation"
        },
        {
            "span": "clinical microbiology",
            "entity": "Discipline"
        },
        {
            "span": "University of Antwerp",
            "entity": "University"
        }
    ]
}