{
    "sentence": "Initially, after the Roman appeared, other authors who refer to the story, for example, Azalais d 'Altier in her poem Tanz salutz e tantas amors and Guido delle Colonne in his Historia destructionis Troiae, continue to use names derived from that of Briseis.",
    "inside_boundary_tokens": [],
    "outside_boundary_tokens": [
        {
            "boundary": "outside",
            "token": "poem",
            "entity_str": "{'span': 'Tanz salutz e tantas amors', 'entity': 'Poem'}",
            "examples": [
                {
                    "sentence": "...refers to a bedtime poem recited in the narrative...",
                    "entity": "poem"
                },
                {
                    "sentence": "...be found in the poem by the australian bush...",
                    "entity": "poem"
                },
                {
                    "sentence": "...any other middle english poem survive...",
                    "entity": "poem"
                },
                {
                    "sentence": "...with his poem yo soy joaquín known...",
                    "entity": "poem"
                },
                {
                    "sentence": "...his most famous poem is the airs of...",
                    "entity": "poem"
                }
            ]
        }
    ]
}