{
    "sentence": "To illustrate the basic principles of bagging, below is an analysis on the relationship between ozone and temperature (data from Rousseeuw and Leroy (1986), analysis done in R).",
    "inside_boundary_tokens": [
        {
            "boundary": "inside",
            "token": "1986",
            "entity_str": "{'span': '1986', 'entity': 'Misc'}",
            "examples": [
                {
                    "sentence": "...magic journeys 1982 and captain eo francis ford coppola 1986...",
                    "entity": "Captain EO"
                },
                {
                    "sentence": "...1982 and captain eo francis ford coppola 1986 starring michael jackson...",
                    "entity": "Francis Ford Coppola"
                },
                {
                    "sentence": "...ford coppola 1986 starring michael jackson being notable examples...",
                    "entity": "Michael Jackson"
                }
            ]
        }
    ],
    "outside_boundary_tokens": [
        {
            "boundary": "outside",
            "token": "analysis",
            "entity_str": "{'span': '1986', 'entity': 'Misc'}",
            "examples": [
                {
                    "sentence": "...text mining information retrieval sentiment analysis see also multimodal sentiment...",
                    "entity": "sentiment analysis"
                },
                {
                    "sentence": "...sentiment analysis see also multimodal sentiment analysis and deep learning x...",
                    "entity": "Multimodal sentiment analysis"
                },
                {
                    "sentence": "...tools and algorithms for data analysis and predictive modeling together...",
                    "entity": "data analysis"
                },
                {
                    "sentence": "...in unsupervised learning are principal component analysis and cluster analysis...",
                    "entity": "principal component analysis"
                },
                {
                    "sentence": "...principal component analysis and cluster analysis...",
                    "entity": "cluster analysis"
                },
                {
                    "sentence": "...principal component analysis pca linear discriminant analysis lda or canonical correlation...",
                    "entity": "linear discriminant analysis"
                },
                {
                    "sentence": "...discriminant analysis lda or canonical correlation analysis cca techniques as a...",
                    "entity": "canonical correlation analysis"
                },
                {
                    "sentence": "...in one step using principal component analysis pca linear discriminant analysis...",
                    "entity": "principal component analysis"
                },
                {
                    "sentence": "...principal component analysis pca linear discriminant analysis lda canonical correlation analysis...",
                    "entity": "linear discriminant analysis"
                },
                {
                    "sentence": "...linear discriminant analysis lda canonical correlation analysis cca or non negative...",
                    "entity": "canonical correlation analysis"
                },
                {
                    "sentence": "...hand gestures interpretation and medical imaging analysis...",
                    "entity": "medical imaging analysis"
                },
                {
                    "sentence": "...also in regression analysis mean squared error often...",
                    "entity": "regression analysis"
                },
                {
                    "sentence": "...popular recognition algorithms include principal component analysis using eigenface s linear...",
                    "entity": "principal component analysis"
                },
                {
                    "sentence": "...analysis using eigenface s linear discriminant analysis elastic matching using the...",
                    "entity": "linear discriminant analysis"
                }
            ]
        }
    ]
}