{
    "id": 54,
    "sentence": "On 24 August 2012, Westenra staged a concert in the Gŵyl Gobaith Music Festival in Wales to support for charities Cancer Research UK, Wales Air Ambulance, CLIC Sargent and HeadtoHeart.",
    "classification": {
        "entity": [
            "Westenra",
            "Gŵyl",
            "Gobaith",
            "Music",
            "Festival",
            "Wales",
            "Cancer",
            "Research",
            "UK",
            "Wales",
            "Air",
            "Ambulance",
            "CLIC",
            "Sargent",
            "HeadtoHeart"
        ],
        "context": [
            "2012",
            ",",
            "staged",
            "a",
            "in",
            "the",
            "in",
            "to",
            "support",
            "for",
            "charities",
            ",",
            ",",
            "and",
            "."
        ],
        "other": [
            "On",
            "24",
            "August",
            "concert"
        ]
    },
    "tokens": [
        "On",
        "24",
        "August",
        "2012",
        ",",
        "Westenra",
        "staged",
        "a",
        "concert",
        "in",
        "the",
        "Gŵyl",
        "Gobaith",
        "Music",
        "Festival",
        "in",
        "Wales",
        "to",
        "support",
        "for",
        "charities",
        "Cancer",
        "Research",
        "UK",
        ",",
        "Wales",
        "Air",
        "Ambulance",
        ",",
        "CLIC",
        "Sargent",
        "and",
        "HeadtoHeart",
        "."
    ],
    "ner_tags": [
        0,
        0,
        0,
        0,
        0,
        43,
        0,
        0,
        0,
        0,
        0,
        29,
        30,
        30,
        30,
        0,
        21,
        0,
        0,
        0,
        0,
        49,
        50,
        50,
        0,
        49,
        50,
        50,
        0,
        49,
        50,
        0,
        49,
        0
    ],
    "true_entities": [
        {
            "span": "Westenra",
            "entity": "Musical Artist"
        },
        {
            "span": "Gŵyl Gobaith Music Festival",
            "entity": "Event"
        },
        {
            "span": "Wales",
            "entity": "Country"
        },
        {
            "span": "Cancer Research UK",
            "entity": "Organisation"
        },
        {
            "span": "Wales Air Ambulance",
            "entity": "Organisation"
        },
        {
            "span": "CLIC Sargent",
            "entity": "Organisation"
        },
        {
            "span": "HeadtoHeart",
            "entity": "Organisation"
        }
    ]
}