{
    "sentence": "The station broadcast Christian feature stories, preaching and teaching to various fundamentalist and Pentecostal denominations and playing Traditional black gospel, Southern gospel, and inspirational music.",
    "false_negative_tokens": [
        {
            "token": "Christian",
            "positive_examples": [
                {
                    "sentence": "...christian alternative music has its roots in...",
                    "entity": "Christian alternative music"
                },
                {
                    "sentence": "...the earliest efforts at christian punk and new wave were...",
                    "entity": "Christian punk"
                }
            ]
        }
    ]
}