{
    "id": 32,
    "sentence": "More recently, fictional representations of artificially intelligent robots in films such as A.I. Artificial Intelligence and Ex Machina and the 2016 TV adaptation of Westworld have engaged audience sympathy for the robots themselves.",
    "classification": {
        "entity": [
            "artificially",
            "intelligent",
            "robots",
            "A.I.",
            "Artificial",
            "Intelligence",
            "Ex",
            "Machina",
            "Westworld"
        ],
        "context": [
            "representations",
            "of",
            "in",
            "films",
            "such",
            "as",
            "and",
            "and",
            "the",
            "adaptation",
            "of",
            "have",
            "engaged"
        ],
        "other": [
            "More",
            "recently",
            ",",
            "fictional",
            "2016",
            "TV",
            "audience",
            "sympathy",
            "for",
            "the",
            "robots",
            "themselves",
            "."
        ]
    },
    "tokens": [
        "More",
        "recently",
        ",",
        "fictional",
        "representations",
        "of",
        "artificially",
        "intelligent",
        "robots",
        "in",
        "films",
        "such",
        "as",
        "A.I.",
        "Artificial",
        "Intelligence",
        "and",
        "Ex",
        "Machina",
        "and",
        "the",
        "2016",
        "TV",
        "adaptation",
        "of",
        "Westworld",
        "have",
        "engaged",
        "audience",
        "sympathy",
        "for",
        "the",
        "robots",
        "themselves",
        "."
    ],
    "ner_tags": [
        0,
        0,
        0,
        0,
        0,
        0,
        59,
        60,
        60,
        0,
        0,
        0,
        0,
        41,
        42,
        42,
        0,
        41,
        42,
        0,
        0,
        0,
        0,
        0,
        0,
        41,
        0,
        0,
        0,
        0,
        0,
        0,
        0,
        0,
        0
    ],
    "true_entities": [
        {
            "span": "artificially intelligent robots",
            "entity": "Product"
        },
        {
            "span": "A.I. Artificial Intelligence",
            "entity": "Misc"
        },
        {
            "span": "Ex Machina",
            "entity": "Misc"
        },
        {
            "span": "Westworld",
            "entity": "Misc"
        }
    ]
}