{
    "id": 118,
    "sentence": "Uma \" pandemia \" (do grego πανδήμιος « de todo o povo ») é uma epidemia de doença infecciosa que se espalha entre a população localizada numa grande região geográfica como, por exemplo, todo o planeta Terra.",
    "classification": {
        "entity": [
            "epidemia",
            "doença",
            "infecciosa",
            "Terra"
        ],
        "context": [
            "é",
            "uma",
            "de",
            "que",
            "se",
            "o",
            "planeta",
            "."
        ],
        "other": [
            "Uma",
            "\"",
            "pandemia",
            "\"",
            "(",
            "do",
            "grego",
            "πανδήμιος",
            "«",
            "de",
            "todo",
            "o",
            "povo",
            "»",
            ")",
            "espalha",
            "entre",
            "a",
            "população",
            "localizada",
            "numa",
            "grande",
            "região",
            "geográfica",
            "como",
            ",",
            "por",
            "exemplo",
            ",",
            "todo"
        ]
    },
    "tokens": [
        "Uma",
        "\"",
        "pandemia",
        "\"",
        "(",
        "do",
        "grego",
        "πανδήμιος",
        "«",
        "de",
        "todo",
        "o",
        "povo",
        "»",
        ")",
        "é",
        "uma",
        "epidemia",
        "de",
        "doença",
        "infecciosa",
        "que",
        "se",
        "espalha",
        "entre",
        "a",
        "população",
        "localizada",
        "numa",
        "grande",
        "região",
        "geográfica",
        "como",
        ",",
        "por",
        "exemplo",
        ",",
        "todo",
        "o",
        "planeta",
        "Terra",
        "."
    ],
    "ner_tags": [
        0,
        0,
        0,
        0,
        0,
        0,
        0,
        0,
        0,
        0,
        0,
        0,
        0,
        0,
        0,
        0,
        0,
        13,
        0,
        13,
        14,
        0,
        0,
        0,
        0,
        0,
        0,
        0,
        0,
        0,
        0,
        0,
        0,
        0,
        0,
        0,
        0,
        0,
        0,
        0,
        11,
        0
    ],
    "true_entities": [
        {
            "span": "epidemia",
            "entity": "Doença"
        },
        {
            "span": "doença infecciosa",
            "entity": "Doença"
        },
        {
            "span": "Terra",
            "entity": "Corpo celeste"
        }
    ]
}