{
    "id": 187,
    "sentence": "No ano seguinte, ele foi promovido para a equipe principal, e estreou em 3 de agosto do mesmo ano, entrando no intervalo de uma vitória sobre o Juventus pela Copa Paulista.",
    "classification": {
        "entity": [
            "Juventus",
            "Copa",
            "Paulista"
        ],
        "context": [
            "sobre",
            "o",
            "pela",
            "."
        ],
        "other": [
            "No",
            "ano",
            "seguinte",
            ",",
            "ele",
            "foi",
            "promovido",
            "para",
            "a",
            "equipe",
            "principal",
            ",",
            "e",
            "estreou",
            "em",
            "3",
            "de",
            "agosto",
            "do",
            "mesmo",
            "ano",
            ",",
            "entrando",
            "no",
            "intervalo",
            "de",
            "uma",
            "vitória"
        ]
    },
    "tokens": [
        "No",
        "ano",
        "seguinte",
        ",",
        "ele",
        "foi",
        "promovido",
        "para",
        "a",
        "equipe",
        "principal",
        ",",
        "e",
        "estreou",
        "em",
        "3",
        "de",
        "agosto",
        "do",
        "mesmo",
        "ano",
        ",",
        "entrando",
        "no",
        "intervalo",
        "de",
        "uma",
        "vitória",
        "sobre",
        "o",
        "Juventus",
        "pela",
        "Copa",
        "Paulista",
        "."
    ],
    "ner_tags": [
        0,
        0,
        0,
        0,
        0,
        0,
        0,
        0,
        0,
        0,
        0,
        0,
        0,
        0,
        0,
        0,
        0,
        0,
        0,
        0,
        0,
        0,
        0,
        0,
        0,
        0,
        0,
        0,
        0,
        0,
        3,
        0,
        15,
        16,
        0
    ],
    "true_entities": [
        {
            "span": "Juventus",
            "entity": "Organização"
        },
        {
            "span": "Copa Paulista",
            "entity": "Evento"
        }
    ]
}