{
    "id": 28,
    "sentence": "Os portos de ancoragem foram reforçados para acomodar módulos de 20 toneladas baseadas na TKS.",
    "classification": {
        "entity": [
            "TKS"
        ],
        "context": [
            "baseadas",
            "na",
            "."
        ],
        "other": [
            "Os",
            "portos",
            "de",
            "ancoragem",
            "foram",
            "reforçados",
            "para",
            "acomodar",
            "módulos",
            "de",
            "20",
            "toneladas"
        ]
    },
    "tokens": [
        "Os",
        "portos",
        "de",
        "ancoragem",
        "foram",
        "reforçados",
        "para",
        "acomodar",
        "módulos",
        "de",
        "20",
        "toneladas",
        "baseadas",
        "na",
        "TKS",
        "."
    ],
    "ner_tags": [
        0,
        0,
        0,
        0,
        0,
        0,
        0,
        0,
        0,
        0,
        0,
        0,
        0,
        0,
        29,
        0
    ],
    "true_entities": [
        {
            "span": "TKS",
            "entity": "Veículo"
        }
    ]
}