{
    "id": 14,
    "sentence": "Portanto, a proclamação da inconstitucionalidade da Lei Complementar Distrital nº 85, de 13 de fevereiro de 1998, com efeitos ex tunc e eficácia erga omnes é medida que se impõe. ” (ADI 2010002007992-9, Conselho Especial, Relator Desembargador NATANAEL CAETANO, julgado em 14/9/2010, DJ-e de 17/11/2010 p. 44) (grifo nosso) “ AÇÃO DIRETA DE INCONSTITUCIONALIDADE.",
    "classification": {
        "entity": [
            "Lei",
            "Complementar",
            "Distrital",
            "nº",
            "85",
            "13",
            "de",
            "fevereiro",
            "de",
            "1998",
            "ADI",
            "2010002007992-9",
            "Conselho",
            "Especial",
            "NATANAEL",
            "CAETANO",
            "14/9/2010",
            "17/11/2010"
        ],
        "context": [
            "inconstitucionalidade",
            "da",
            ",",
            "de",
            ",",
            "com",
            "”",
            "(",
            ",",
            ",",
            "Relator",
            "Desembargador",
            ",",
            "julgado",
            "em",
            ",",
            "DJ-e",
            "de",
            "p.",
            "44"
        ],
        "other": [
            "Portanto",
            ",",
            "a",
            "proclamação",
            "da",
            "efeitos",
            "ex",
            "tunc",
            "e",
            "eficácia",
            "erga",
            "omnes",
            "é",
            "medida",
            "que",
            "se",
            "impõe.",
            ")",
            "(",
            "grifo",
            "nosso",
            ")",
            "“",
            "AÇÃO",
            "DIRETA",
            "DE",
            "INCONSTITUCIONALIDADE",
            "."
        ]
    },
    "tokens": [
        "Portanto",
        ",",
        "a",
        "proclamação",
        "da",
        "inconstitucionalidade",
        "da",
        "Lei",
        "Complementar",
        "Distrital",
        "nº",
        "85",
        ",",
        "de",
        "13",
        "de",
        "fevereiro",
        "de",
        "1998",
        ",",
        "com",
        "efeitos",
        "ex",
        "tunc",
        "e",
        "eficácia",
        "erga",
        "omnes",
        "é",
        "medida",
        "que",
        "se",
        "impõe.",
        "”",
        "(",
        "ADI",
        "2010002007992-9",
        ",",
        "Conselho",
        "Especial",
        ",",
        "Relator",
        "Desembargador",
        "NATANAEL",
        "CAETANO",
        ",",
        "julgado",
        "em",
        "14/9/2010",
        ",",
        "DJ-e",
        "de",
        "17/11/2010",
        "p.",
        "44",
        ")",
        "(",
        "grifo",
        "nosso",
        ")",
        "“",
        "AÇÃO",
        "DIRETA",
        "DE",
        "INCONSTITUCIONALIDADE",
        "."
    ],
    "ner_tags": [
        0,
        0,
        0,
        0,
        0,
        0,
        0,
        9,
        10,
        10,
        10,
        10,
        0,
        0,
        7,
        8,
        8,
        8,
        8,
        0,
        0,
        0,
        0,
        0,
        0,
        0,
        0,
        0,
        0,
        0,
        0,
        0,
        0,
        0,
        0,
        11,
        12,
        0,
        3,
        4,
        0,
        0,
        0,
        1,
        2,
        0,
        0,
        0,
        7,
        0,
        0,
        0,
        7,
        0,
        0,
        0,
        0,
        0,
        0,
        0,
        0,
        0,
        0,
        0,
        0,
        0
    ],
    "true_entities": [
        {
            "span": "Lei Complementar Distrital nº 85",
            "entity": "Legislação"
        },
        {
            "span": "13 de fevereiro de 1998",
            "entity": "Tempo"
        },
        {
            "span": "ADI 2010002007992-9",
            "entity": "Jurisprudência"
        },
        {
            "span": "Conselho Especial",
            "entity": "Organização"
        },
        {
            "span": "NATANAEL CAETANO",
            "entity": "Pessoa"
        },
        {
            "span": "14/9/2010",
            "entity": "Tempo"
        },
        {
            "span": "17/11/2010",
            "entity": "Tempo"
        }
    ]
}