{
    "id": 47,
    "sentence": "Compete privativamenteao Governador do Distrito Federal: (...) VI iniciar o processo legislativo, na forma e nos casos previstos nesta Lei Orgânica.",
    "classification": {
        "entity": [
            "Distrito",
            "Federal"
        ],
        "context": [
            "Governador",
            "do",
            ":",
            "("
        ],
        "other": [
            "Compete",
            "privativamenteao",
            "...",
            ")",
            "VI",
            "iniciar",
            "o",
            "processo",
            "legislativo",
            ",",
            "na",
            "forma",
            "e",
            "nos",
            "casos",
            "previstos",
            "nesta",
            "Lei",
            "Orgânica",
            "."
        ]
    },
    "tokens": [
        "Compete",
        "privativamenteao",
        "Governador",
        "do",
        "Distrito",
        "Federal",
        ":",
        "(",
        "...",
        ")",
        "VI",
        "iniciar",
        "o",
        "processo",
        "legislativo",
        ",",
        "na",
        "forma",
        "e",
        "nos",
        "casos",
        "previstos",
        "nesta",
        "Lei",
        "Orgânica",
        "."
    ],
    "ner_tags": [
        0,
        0,
        0,
        0,
        5,
        6,
        0,
        0,
        0,
        0,
        0,
        0,
        0,
        0,
        0,
        0,
        0,
        0,
        0,
        0,
        0,
        0,
        0,
        0,
        0,
        0
    ],
    "true_entities": [
        {
            "span": "Distrito Federal",
            "entity": "Localização"
        }
    ]
}