{
    "id": 92,
    "sentence": "(EDcl no AgInt no AREsp 892.042/SC, Rel. Ministro MAURO CAMPBELL MARQUES, SEGUNDA TURMA, julgado em PODER JUDICIÁRIO DO ESTADO DO ACRE Segunda Câmara Cível 12 Endereço: Rua Tribunal de Justiça, s/n, Via Verde, CEP 69.915-631, Tel. 68 3302-0444/0445, Rio Branco-AC - Mod. 500258 - Autos n.º 1002199-81.2017.8.01.0000/50000 02/02/2017, DJe 08/02/2017).",
    "classification": {
        "entity": [
            "EDcl",
            "no",
            "AgInt",
            "no",
            "AREsp",
            "892.042/SC",
            "MAURO",
            "CAMPBELL",
            "MARQUES",
            "SEGUNDA",
            "TURMA",
            "ESTADO",
            "DO",
            "ACRE",
            "Segunda",
            "Câmara",
            "Cível",
            "Rua",
            "Tribunal",
            "de",
            "Justiça",
            "Via",
            "Verde",
            "Rio",
            "Branco-AC",
            "Autos",
            "n.º",
            "1002199-81.2017.8.01.0000/50000",
            "02/02/2017",
            "08/02/2017"
        ],
        "context": [
            "(",
            ",",
            "Rel",
            ".",
            "Ministro",
            ",",
            ",",
            "julgado",
            "JUDICIÁRIO",
            "DO",
            "12",
            "Endereço",
            ":",
            ",",
            "s/n",
            ",",
            ",",
            "CEP",
            "3302-0444/0445",
            ",",
            "-",
            "Mod",
            "500258",
            "-",
            ",",
            "DJe",
            ")",
            "."
        ],
        "other": [
            "em",
            "PODER",
            "69.915-631",
            ",",
            "Tel.",
            "68",
            "."
        ]
    },
    "tokens": [
        "(",
        "EDcl",
        "no",
        "AgInt",
        "no",
        "AREsp",
        "892.042/SC",
        ",",
        "Rel",
        ".",
        "Ministro",
        "MAURO",
        "CAMPBELL",
        "MARQUES",
        ",",
        "SEGUNDA",
        "TURMA",
        ",",
        "julgado",
        "em",
        "PODER",
        "JUDICIÁRIO",
        "DO",
        "ESTADO",
        "DO",
        "ACRE",
        "Segunda",
        "Câmara",
        "Cível",
        "12",
        "Endereço",
        ":",
        "Rua",
        "Tribunal",
        "de",
        "Justiça",
        ",",
        "s/n",
        ",",
        "Via",
        "Verde",
        ",",
        "CEP",
        "69.915-631",
        ",",
        "Tel.",
        "68",
        "3302-0444/0445",
        ",",
        "Rio",
        "Branco-AC",
        "-",
        "Mod",
        ".",
        "500258",
        "-",
        "Autos",
        "n.º",
        "1002199-81.2017.8.01.0000/50000",
        "02/02/2017",
        ",",
        "DJe",
        "08/02/2017",
        ")",
        "."
    ],
    "ner_tags": [
        0,
        11,
        12,
        12,
        12,
        12,
        12,
        0,
        0,
        0,
        0,
        1,
        2,
        2,
        0,
        3,
        4,
        0,
        0,
        0,
        0,
        0,
        0,
        5,
        6,
        6,
        3,
        4,
        4,
        0,
        0,
        0,
        5,
        6,
        6,
        6,
        0,
        0,
        0,
        5,
        6,
        0,
        0,
        0,
        0,
        0,
        0,
        0,
        0,
        5,
        6,
        0,
        0,
        0,
        0,
        0,
        11,
        12,
        12,
        7,
        0,
        0,
        7,
        0,
        0
    ],
    "true_entities": [
        {
            "span": "EDcl no AgInt no AREsp 892.042/SC",
            "entity": "Jurisprudência"
        },
        {
            "span": "MAURO CAMPBELL MARQUES",
            "entity": "Pessoa"
        },
        {
            "span": "SEGUNDA TURMA",
            "entity": "Organização"
        },
        {
            "span": "ESTADO DO ACRE",
            "entity": "Localização"
        },
        {
            "span": "Segunda Câmara Cível",
            "entity": "Organização"
        },
        {
            "span": "Rua Tribunal de Justiça",
            "entity": "Localização"
        },
        {
            "span": "Via Verde",
            "entity": "Localização"
        },
        {
            "span": "Rio Branco-AC",
            "entity": "Localização"
        },
        {
            "span": "Autos n.º 1002199-81.2017.8.01.0000/50000",
            "entity": "Jurisprudência"
        },
        {
            "span": "02/02/2017",
            "entity": "Tempo"
        },
        {
            "span": "08/02/2017",
            "entity": "Tempo"
        }
    ]
}