{
    "sentence": "In addition Alexander Ovechkin, the PutinTeam movement also included many Russian sportsmen, actors, musicians and social activists: Evgeni Malkin, Yelena Isinbayeva, Sergey Karjakin, Sergey Tetyukhin, Nikolay Rastorguyev, Polina Gagarina, Dima Bilan, Ilya Kovalchuk, Nyusha, Andrey Merzlikin, Pavel Bure, Evgeni Plushenko, Nikolay Baskov, Sergei Krikalev, Mikhail Galustyan, Alexander Legkov, Anton Shipulin, Ivan Tcherezov, Alexandr Karelin and others.",
    "false_negative_tokens": [
        {
            "token": "Russian",
            "positive_examples": [
                {
                    "sentence": "...and opposition parties the communist party of the russian federation and liberal democratic party...",
                    "entity": "Communist Party of the Russian Federation"
                },
                {
                    "sentence": "...polish nobles who resisted russian rule and members of...",
                    "entity": "Russian"
                }
            ]
        }
    ]
}