{
    "id": 0,
    "sentence": "Parties with mainly Eurosceptic views are the ruling United Russia, and opposition parties the Communist Party of the Russian Federation and Liberal Democratic Party of Russia.",
    "classification": {
        "entity": [
            "United",
            "Russia",
            "Communist",
            "Party",
            "of",
            "the",
            "Russian",
            "Federation",
            "Liberal",
            "Democratic",
            "Party",
            "of",
            "Russia"
        ],
        "context": [
            "the",
            "ruling",
            ",",
            "and",
            "parties",
            "the",
            "and",
            "."
        ],
        "other": [
            "Parties",
            "with",
            "mainly",
            "Eurosceptic",
            "views",
            "are",
            "opposition"
        ]
    },
    "tokens": [
        "Parties",
        "with",
        "mainly",
        "Eurosceptic",
        "views",
        "are",
        "the",
        "ruling",
        "United",
        "Russia",
        ",",
        "and",
        "opposition",
        "parties",
        "the",
        "Communist",
        "Party",
        "of",
        "the",
        "Russian",
        "Federation",
        "and",
        "Liberal",
        "Democratic",
        "Party",
        "of",
        "Russia",
        "."
    ],
    "ner_tags": [
        0,
        0,
        0,
        0,
        0,
        0,
        0,
        0,
        55,
        56,
        0,
        0,
        0,
        0,
        0,
        55,
        56,
        56,
        56,
        56,
        56,
        0,
        55,
        56,
        56,
        56,
        56,
        0
    ],
    "true_entities": [
        {
            "span": "United Russia",
            "entity": "Political Party"
        },
        {
            "span": "Communist Party of the Russian Federation",
            "entity": "Political Party"
        },
        {
            "span": "Liberal Democratic Party of Russia",
            "entity": "Political Party"
        }
    ]
}