{
    "id": 139,
    "sentence": "Excluding the Japanese Communist Party, the coalition was backed by all of the former opposition parties, which included the newly formed JNP, the Japan Socialist Party, the Japan Renewal Party (Shinseito), Komeito, the Democratic Socialist Party, the Socialist Democratic Federation, and the New Party Sakigake, who together controlled 243 seats in the House of Representatives.",
    "classification": {
        "entity": [
            "Japanese",
            "Communist",
            "Party",
            "JNP",
            "Japan",
            "Socialist",
            "Party",
            "Japan",
            "Renewal",
            "Party",
            "Shinseito",
            "Komeito",
            "Democratic",
            "Socialist",
            "Party",
            "Socialist",
            "Democratic",
            "Federation",
            "New",
            "Party",
            "Sakigake"
        ],
        "context": [
            "Excluding",
            "the",
            ",",
            "the",
            "newly",
            "formed",
            ",",
            "the",
            ",",
            "the",
            "(",
            ")",
            ",",
            ",",
            "the",
            ",",
            "the",
            ",",
            "and",
            "the",
            ",",
            "who"
        ],
        "other": [
            "coalition",
            "was",
            "backed",
            "by",
            "all",
            "of",
            "the",
            "former",
            "opposition",
            "parties",
            ",",
            "which",
            "included",
            "the",
            "together",
            "controlled",
            "243",
            "seats",
            "in",
            "the",
            "House",
            "of",
            "Representatives",
            "."
        ]
    },
    "tokens": [
        "Excluding",
        "the",
        "Japanese",
        "Communist",
        "Party",
        ",",
        "the",
        "coalition",
        "was",
        "backed",
        "by",
        "all",
        "of",
        "the",
        "former",
        "opposition",
        "parties",
        ",",
        "which",
        "included",
        "the",
        "newly",
        "formed",
        "JNP",
        ",",
        "the",
        "Japan",
        "Socialist",
        "Party",
        ",",
        "the",
        "Japan",
        "Renewal",
        "Party",
        "(",
        "Shinseito",
        ")",
        ",",
        "Komeito",
        ",",
        "the",
        "Democratic",
        "Socialist",
        "Party",
        ",",
        "the",
        "Socialist",
        "Democratic",
        "Federation",
        ",",
        "and",
        "the",
        "New",
        "Party",
        "Sakigake",
        ",",
        "who",
        "together",
        "controlled",
        "243",
        "seats",
        "in",
        "the",
        "House",
        "of",
        "Representatives",
        "."
    ],
    "ner_tags": [
        0,
        0,
        55,
        56,
        56,
        0,
        0,
        0,
        0,
        0,
        0,
        0,
        0,
        0,
        0,
        0,
        0,
        0,
        0,
        0,
        0,
        0,
        0,
        55,
        0,
        0,
        55,
        56,
        56,
        0,
        0,
        55,
        56,
        56,
        0,
        55,
        0,
        0,
        55,
        0,
        0,
        55,
        56,
        56,
        0,
        0,
        55,
        56,
        56,
        0,
        0,
        0,
        55,
        56,
        56,
        0,
        0,
        0,
        0,
        0,
        0,
        0,
        0,
        0,
        0,
        0,
        0
    ],
    "true_entities": [
        {
            "span": "Japanese Communist Party",
            "entity": "Political Party"
        },
        {
            "span": "JNP",
            "entity": "Political Party"
        },
        {
            "span": "Japan Socialist Party",
            "entity": "Political Party"
        },
        {
            "span": "Japan Renewal Party",
            "entity": "Political Party"
        },
        {
            "span": "Shinseito",
            "entity": "Political Party"
        },
        {
            "span": "Komeito",
            "entity": "Political Party"
        },
        {
            "span": "Democratic Socialist Party",
            "entity": "Political Party"
        },
        {
            "span": "Socialist Democratic Federation",
            "entity": "Political Party"
        },
        {
            "span": "New Party Sakigake",
            "entity": "Political Party"
        }
    ]
}