{
    "id": 44,
    "sentence": "Genscher was one of the FDP's driving forces when, in 1982, the party switched sides from its coalition with the SPD to support the Christian Democratic Union of Germany in their Constructive vote of no confidence to have incumbent Helmut Schmidt replaced with opposition leader Helmut Kohl as Chancellor.",
    "classification": {
        "entity": [
            "Genscher",
            "FDP",
            "SPD",
            "Christian",
            "Democratic",
            "Union",
            "of",
            "Germany",
            "Helmut",
            "Schmidt",
            "Helmut",
            "Kohl"
        ],
        "context": [
            "was",
            "one",
            "of",
            "the",
            "'s",
            "driving",
            "with",
            "the",
            "to",
            "support",
            "the",
            "in",
            "their",
            "have",
            "incumbent",
            "replaced",
            "with",
            "opposition",
            "leader",
            "as",
            "Chancellor"
        ],
        "other": [
            "forces",
            "when",
            ",",
            "in",
            "1982",
            ",",
            "the",
            "party",
            "switched",
            "sides",
            "from",
            "its",
            "coalition",
            "Constructive",
            "vote",
            "of",
            "no",
            "confidence",
            "to",
            "."
        ]
    },
    "tokens": [
        "Genscher",
        "was",
        "one",
        "of",
        "the",
        "FDP",
        "'s",
        "driving",
        "forces",
        "when",
        ",",
        "in",
        "1982",
        ",",
        "the",
        "party",
        "switched",
        "sides",
        "from",
        "its",
        "coalition",
        "with",
        "the",
        "SPD",
        "to",
        "support",
        "the",
        "Christian",
        "Democratic",
        "Union",
        "of",
        "Germany",
        "in",
        "their",
        "Constructive",
        "vote",
        "of",
        "no",
        "confidence",
        "to",
        "have",
        "incumbent",
        "Helmut",
        "Schmidt",
        "replaced",
        "with",
        "opposition",
        "leader",
        "Helmut",
        "Kohl",
        "as",
        "Chancellor",
        "."
    ],
    "ner_tags": [
        57,
        0,
        0,
        0,
        0,
        55,
        0,
        0,
        0,
        0,
        0,
        0,
        0,
        0,
        0,
        0,
        0,
        0,
        0,
        0,
        0,
        0,
        0,
        55,
        0,
        0,
        0,
        55,
        56,
        56,
        56,
        56,
        0,
        0,
        0,
        0,
        0,
        0,
        0,
        0,
        0,
        0,
        57,
        58,
        0,
        0,
        0,
        0,
        57,
        58,
        0,
        0,
        0
    ],
    "true_entities": [
        {
            "span": "Genscher",
            "entity": "Politician"
        },
        {
            "span": "FDP",
            "entity": "Political Party"
        },
        {
            "span": "SPD",
            "entity": "Political Party"
        },
        {
            "span": "Christian Democratic Union of Germany",
            "entity": "Political Party"
        },
        {
            "span": "Helmut Schmidt",
            "entity": "Politician"
        },
        {
            "span": "Helmut Kohl",
            "entity": "Politician"
        }
    ]
}