{
    "id": 88,
    "sentence": "In 1961, Tito co-founded the movement with Egypt's Gamal Abdel Nasser, India's Jawaharlal Nehru, Indonesia's Sukarno and Ghana's Kwame Nkrumah, in an action called The Initiative of Five (Tito, Nehru, Nasser, Sukarno, Nkrumah), thus establishing strong ties with third world countries.",
    "classification": {
        "entity": [
            "Tito",
            "Egypt",
            "Gamal",
            "Abdel",
            "Nasser",
            "India",
            "Jawaharlal",
            "Nehru",
            "Indonesia",
            "Sukarno",
            "Ghana",
            "Kwame",
            "Nkrumah",
            "Tito",
            "Nehru",
            "Nasser",
            "Sukarno",
            "Nkrumah"
        ],
        "context": [
            "1961",
            ",",
            "co-founded",
            "the",
            "movement",
            "with",
            "'s",
            ",",
            "'s",
            ",",
            "'s",
            "and",
            "'s",
            ",",
            "in",
            "Five",
            "(",
            ",",
            ",",
            ",",
            ",",
            ")",
            ","
        ],
        "other": [
            "In",
            "an",
            "action",
            "called",
            "The",
            "Initiative",
            "of",
            "thus",
            "establishing",
            "strong",
            "ties",
            "with",
            "third",
            "world",
            "countries",
            "."
        ]
    },
    "tokens": [
        "In",
        "1961",
        ",",
        "Tito",
        "co-founded",
        "the",
        "movement",
        "with",
        "Egypt",
        "'s",
        "Gamal",
        "Abdel",
        "Nasser",
        ",",
        "India",
        "'s",
        "Jawaharlal",
        "Nehru",
        ",",
        "Indonesia",
        "'s",
        "Sukarno",
        "and",
        "Ghana",
        "'s",
        "Kwame",
        "Nkrumah",
        ",",
        "in",
        "an",
        "action",
        "called",
        "The",
        "Initiative",
        "of",
        "Five",
        "(",
        "Tito",
        ",",
        "Nehru",
        ",",
        "Nasser",
        ",",
        "Sukarno",
        ",",
        "Nkrumah",
        ")",
        ",",
        "thus",
        "establishing",
        "strong",
        "ties",
        "with",
        "third",
        "world",
        "countries",
        "."
    ],
    "ner_tags": [
        0,
        0,
        0,
        57,
        0,
        0,
        0,
        0,
        21,
        0,
        57,
        58,
        58,
        0,
        21,
        0,
        57,
        58,
        0,
        21,
        0,
        57,
        0,
        21,
        0,
        57,
        58,
        0,
        0,
        0,
        0,
        0,
        0,
        0,
        0,
        0,
        0,
        57,
        0,
        57,
        0,
        57,
        0,
        57,
        0,
        57,
        0,
        0,
        0,
        0,
        0,
        0,
        0,
        0,
        0,
        0,
        0
    ],
    "true_entities": [
        {
            "span": "Tito",
            "entity": "Politician"
        },
        {
            "span": "Egypt",
            "entity": "Country"
        },
        {
            "span": "Gamal Abdel Nasser",
            "entity": "Politician"
        },
        {
            "span": "India",
            "entity": "Country"
        },
        {
            "span": "Jawaharlal Nehru",
            "entity": "Politician"
        },
        {
            "span": "Indonesia",
            "entity": "Country"
        },
        {
            "span": "Sukarno",
            "entity": "Politician"
        },
        {
            "span": "Ghana",
            "entity": "Country"
        },
        {
            "span": "Kwame Nkrumah",
            "entity": "Politician"
        },
        {
            "span": "Nehru",
            "entity": "Politician"
        },
        {
            "span": "Nasser",
            "entity": "Politician"
        },
        {
            "span": "Nkrumah",
            "entity": "Politician"
        }
    ]
}