{
    "sentence": "In 1990, she contributed a cover of You Do Something to Me to the Cole Porter tribute / AIDS fundraising album Red Hot + Blue produced by the Red Hot Organization.",
    "false_negative_tokens": [
        {
            "token": "Porter",
            "entity_count": 1,
            "context_count": 0,
            "other_count": 0,
            "positive_examples": [
                {
                    "sentence": "Despite the appeal of the Nashville sound, many traditional country artists emerged during this period and dominated the genre: Loretta Lynn, Merle Haggard, Buck Owens, Porter Wagoner, George Jones, and Sonny James among them.",
                    "true_entities": [
                        {
                            "span": "the Nashville sound",
                            "entity": "Music Genre"
                        },
                        {
                            "span": "Loretta Lynn",
                            "entity": "Musical Artist"
                        },
                        {
                            "span": "Merle Haggard",
                            "entity": "Musical Artist"
                        },
                        {
                            "span": "Buck Owens",
                            "entity": "Musical Artist"
                        },
                        {
                            "span": "Porter Wagoner",
                            "entity": "Musical Artist"
                        },
                        {
                            "span": "George Jones",
                            "entity": "Musical Artist"
                        },
                        {
                            "span": "Sonny James",
                            "entity": "Musical Artist"
                        }
                    ]
                }
            ],
            "hard_negative_examples": [],
            "negative_examples": []
        }
    ]
}